{
  "faction": "/r/TheClickOwO",
  "contact": "https://github.com/Aras14HD/ClickPlace/issues",
  "templates": [
    {
      "name": "Emotional Support Demons",
      "sources": [
        "https://raw.githubusercontent.com/Aras14HD/ClickPlace/main/Current.png"
      ],
      "x": 2117,
      "y": 1245
    },
    {
      "name": "Swedish demons",
      "sources": [
        "https://raw.githubusercontent.com/Aras14HD/ClickPlace/main/Swedish.png"
      ],
      "x": 1578,
      "y": 772
    }
  ],
  "whitelist": [
    {
      "name": "PridePlace",
      "url": "https://pride.place/template.json"
    },
    {
      "name": "trans.gg",
      "url": "https://trans.gg/template.json"
    }
  ],
  "blacklist": []
}
